pi_zero_pytorch/__init__.py
pi_zero_pytorch/load.py
pi_zero_pytorch/mock.py
pi_zero_pytorch/pi_zero.py
pi_zero_pytorch/tensor_typing.py
pi_zero_pytorch-0.4.67.dist-info/METADATA
pi_zero_pytorch-0.4.67.dist-info/WHEEL
pi_zero_pytorch-0.4.67.dist-info/licenses/LICENSE
pi_zero_pytorch-0.4.67.dist-info/RECORD
