Metadata-Version: 2.4
Name: pi-zero-pytorch
Version: 0.4.67
Summary: π0 in Pytorch
Project-URL: Homepage, https://pypi.org/project/pi-zero-pytorch/
Project-URL: Repository, https://github.com/lucidrains/pi-zero-pytorch
Author-email: Phil Wang <lucidrains@gmail.com>
License: MIT License
License-File: LICENSE
Keywords: artificial intelligence,deep learning,flow policy,robotic foundation model,transformers
Classifier: Development Status :: 4 - Beta
Classifier: Intended Audience :: Developers
Classifier: License :: OSI Approved :: MIT License
Classifier: Programming Language :: Python :: 3.10
Classifier: Topic :: Scientific/Engineering :: Artificial Intelligence
Requires-Python: >=3.10
Requires-Dist: accelerate>=1.6.0
Requires-Dist: assoc-scan>=0.0.2
Requires-Dist: beartype
Requires-Dist: bidirectional-cross-attention
Requires-Dist: einops>=0.8.0
Requires-Dist: einx>=0.3.0
Requires-Dist: ema-pytorch>=0.7.3
Requires-Dist: evolutionary-policy-optimization>=0.1.19
Requires-Dist: hl-gauss-pytorch>=0.1.21
Requires-Dist: hyper-connections>=0.3.12
Requires-Dist: jaxtyping
Requires-Dist: memmap-replay-buffer>=0.0.10
Requires-Dist: pydantic>=2
Requires-Dist: safetensors
Requires-Dist: scipy
Requires-Dist: torch-einops-utils>=0.0.6
Requires-Dist: torch>=2.5
Requires-Dist: torchdiffeq
Requires-Dist: torchtyping>=0.1.5
Requires-Dist: tqdm
Requires-Dist: transformers
Requires-Dist: vit-pytorch>=1.17.3
Requires-Dist: x-evolution>=0.1.15
Requires-Dist: x-mlps-pytorch>=0.0.24
Requires-Dist: x-transformers>=2.4.1
Provides-Extra: examples
Provides-Extra: test
Requires-Dist: pytest; extra == 'test'
Requires-Dist: ruff>=0.4.2; extra == 'test'
Requires-Dist: vit-pytorch>=1.8.7; extra == 'test'
